cai_garland/__init__.py
cai_garland/data/__init__.py
cai_garland/data/context_collator.py
cai_garland/data/context_injection_dataset.py
cai_garland/data/parallel_dataset_loader_hf.py
cai_garland/data/parallel_dataset_prep.py
cai_garland/data/parallel_dataset_sequencing.py
cai_garland/data/segmentation_dataset_prep.py
cai_garland/data/siamese_collator.py
cai_garland/data/synthetic_nllb_data.py
cai_garland/data/dataset_prep.config/parallel_dataset_prep.yaml
cai_garland/data/dataset_prep.config/segmentation_dataset_prep.yaml
cai_garland/data/dataset_prep.config/symbol_cleaning_bo.json
cai_garland/data/dataset_prep.config/symbol_cleaning_en.json
cai_garland/data/dataset_prep.config/symbol_cleaning_en_no_skip.json
cai_garland/data/dataset_prep.config/synthetic_nllb_data.yaml
cai_garland/data/dataset_prep.config/output/uncased-no-accents.yaml
cai_garland/data/dataset_prep.config/processing/local-dask.yaml
cai_garland/data/dataset_prep.config/stages/concatted-registers-sequenced.yaml
cai_garland/data/dataset_prep.config/stages/concatted-registers.yaml
cai_garland/data/dataset_prep.config/stages/context-embeddings-from-folios-cased.yaml
cai_garland/data/dataset_prep.config/stages/context-embeddings-from-folios.yaml
cai_garland/data/dataset_prep.config/stages/dictionary.yaml
cai_garland/data/dataset_prep.config/stages/folio-registers.yaml
cai_garland/data/dataset_prep.config/stages/naive-concats-sequenced-cased.yaml
cai_garland/data/dataset_prep.config/stages/naive-concats-sequenced.yaml
cai_garland/data/dataset_prep.config/stages/naive-concats.yaml
cai_garland/data/dataset_prep.config/stages/naive-unconcatted.yaml
cai_garland/data/dataset_prep.config/stages/registers.yaml
cai_garland/data/dataset_prep.config/stages/unconcatted-registers-sequenced.yaml
cai_garland/data/dataset_prep.config/stages/concat/concat-future-context.yaml
cai_garland/data/dataset_prep.config/stages/concat/concat.yaml
cai_garland/data/dataset_prep.config/stages/concat/no-concat.yaml
compassionai_garland-0.2.1.dist-info/LICENSE
compassionai_garland-0.2.1.dist-info/METADATA
compassionai_garland-0.2.1.dist-info/WHEEL
compassionai_garland-0.2.1.dist-info/top_level.txt
compassionai_garland-0.2.1.dist-info/RECORD
